README.txt
setup.py
dockyard/__init__.py
dockyard/entry.py
dockyard.egg-info/PKG-INFO
dockyard.egg-info/SOURCES.txt
dockyard.egg-info/dependency_links.txt
dockyard.egg-info/entry_points.txt
dockyard.egg-info/requires.txt
dockyard.egg-info/top_level.txt
dockyard/core/__init__.py
dockyard/core/command_interpreter.py
dockyard/core/command_line_interpreter.py
dockyard/core/lib/__init__.py
dockyard/core/lib/config_parser.py
dockyard/core/lib/dict2table.py
dockyard/core/lib/dns.py
dockyard/core/lib/docker_image.py
dockyard/core/lib/docker_wrapper.py
dockyard/core/lib/dockyard.py
dockyard/core/lib/util.py
dockyard/core/lib/vagrant_wrapper.py
dockyard/core/plugin_docker/__init__.py
dockyard/core/plugin_docker/command_interpreter.py
dockyard/core/plugin_docker/plugin.py
dockyard/core/plugin_dockyard/__init__.py
dockyard/core/plugin_dockyard/command_interpreter.py
dockyard/core/plugin_dockyard/plugin.py
dockyard/core/plugin_stack/__init__.py
dockyard/core/plugin_stack/command_interpreter.py
dockyard/core/plugin_stack/plugin.py
dockyard/core/test/__init__.py
dockyard/core/test/config_parser_spec.py