Metadata-Version: 1.0
Name: dockyard
Version: 0.2
Summary: Light-weight CLI for development using Vagrant + Docker
Home-page: https://github.com/smysnk/dockyard
Author: Joshua Bellamy-Henn
Author-email: josh@psidox.com
License: UNKNOWN
Keywords: docker vagrant dockyard
Platform: UNKNOWN
